cherrypy_psycopg2/__init__.py
cherrypy_psycopg2-2.0.dist-info/LICENSE
cherrypy_psycopg2-2.0.dist-info/METADATA
cherrypy_psycopg2-2.0.dist-info/WHEEL
cherrypy_psycopg2-2.0.dist-info/top_level.txt
cherrypy_psycopg2-2.0.dist-info/RECORD
