Metadata-Version: 2.1
Name: cherrypy-psycopg2
Version: 2.0
Summary: CherryPy tool to manage Psycopg 2 database connections
Author: Graham Clinch
Author-email: g.clinch@lancaster.ac.uk
Classifier: Development Status :: 5 - Production/Stable
Classifier: Framework :: CherryPy
Classifier: License :: OSI Approved :: Apache Software License
Classifier: Topic :: Database
License-File: LICENSE
Requires-Dist: CherryPy
Requires-Dist: psycopg2
